eaf/__init__.py
eaf/app.py
eaf/clock.py
eaf/core.py
eaf/errors.py
eaf/handlers.py
eaf/meta.py
eaf/render.py
eaf/state.py
eaf/timer.py
eaf-0.2.2.dist-info/LICENSE
eaf-0.2.2.dist-info/WHEEL
eaf-0.2.2.dist-info/METADATA
eaf-0.2.2.dist-info/RECORD
