Metadata-Version: 2.1
Name: eaf
Version: 0.2.2
Summary: Enterprise Application Framework
Home-page: https://github.com/pkulev/eaf
License: MIT
Keywords: application,framework
Author: Pavel Kulyov
Author-email: kulyov.pavel@gmail.com
Requires-Python: >=3.7,<4.0
Classifier: Development Status :: 3 - Alpha
Classifier: Intended Audience :: Developers
Classifier: License :: OSI Approved :: MIT License
Classifier: Operating System :: POSIX :: Linux
Classifier: Programming Language :: Python :: 3
Classifier: Programming Language :: Python :: 3.7
Classifier: Programming Language :: Python :: 3.8
Requires-Dist: tornado (>=6.0.4,<7.0.0)
Project-URL: Repository, https://github.com/pkulev/eaf
